h5obj/__init__.py
h5obj/dummy.py
h5obj/tools.py
h5obj-0.1.0.dist-info/METADATA
h5obj-0.1.0.dist-info/WHEEL
h5obj-0.1.0.dist-info/licenses/LICENSE.txt
h5obj-0.1.0.dist-info/RECORD
