Metadata-Version: 2.1
Name: h5obj
Version: 0.1.0
Summary: Store native Python objects in HDF5 files using strings in json format. Defines wrappers for h5py.File and h5py.Group.
Project-URL: Source, https://github.com/proggy/h5obj
Project-URL: Homepage, https://github.com/proggy/h5obj
Project-URL: Bug Tracker, https://github.com/proggy/h5obj/issues
Author-email: Daniel Jung <proggy-contact@mailbox.org>
Maintainer-email: Daniel Jung <proggy-contact@mailbox.org>
License-File: LICENSE.txt
Classifier: License :: OSI Approved :: GNU General Public License v2 (GPLv2)
Classifier: Operating System :: OS Independent
Classifier: Programming Language :: Python :: 3
Requires-Python: >=3.7
Requires-Dist: cofunc
Requires-Dist: h5py
Requires-Dist: numpy
